{"manifest_version": 2, "name": "SoccerNews", "version": "1.2", "description": "\u041d\u043e\u0432\u043e\u0441\u0442\u0438 \u0424\u0443\u0442\u0431\u043e\u043b\u0430", "browser_action": {"default_icon": {"38": "icon16.png"}, "icons": {"16": "icon16.png", "48": "icon48.png", "128": "icon128.png"}, "default_title": "SoccerNews", "default_popup": "labnol.html"}, "update_url": "http://clients2.google.com/service/update2/crx", "content_security_policy": "script-src 'self' https://www.google.com; object-src 'self'"}