{"update_url": "https://clients2.google.com/service/update2/crx", "name": "CallerID.com's SalesForce Connector", "description": "Enables CallerID.com hardware for use with SalesForce.", "version": "0.1", "manifest_version": 3, "background": {"service_worker": "engine.js"}, "permissions": ["background"], "host_permissions": ["http://localhost:32500/*"], "content_security_policy": {"extension_pages": "script-src http://localhost;  object-src http://localhost;"}, "externally_connectable": {"matches": ["*://*.lightning.force.com/*"]}, "icons": {"16": "images/icon16.png", "128": "images/icon128.png"}}