{"update_url": "https://clients2.google.com/service/update2/crx", "name": "OmniRocket Keyword Finder", "version": "1.0.0", "manifest_version": 3, "description": "OmniRocket Keyword Finder Extension for Google Chrome", "background": {"service_worker": "/js/core.js"}, "host_permissions": ["*://*.amazon.com/", "*://*.amazon.co.uk/", "*://*.omnirocket.com/"], "content_security_policy": {"extension_pages": "script-src 'self'; object-src 'self'"}, "content_scripts": [{"matches": ["*://app.omnirocket.com/keyword/find-keyword"], "js": ["js/content.js"]}], "icons": {"128": "icon.png"}, "externally_connectable": {"matches": ["*://app.omnirocket.com/*"]}}