{"update_url": "https://clients2.google.com/service/update2/crx", "manifest_version": 3, "name": "GPT AI-Powered Email Assistant for Businesses", "version": "1.0.4", "permissions": ["activeTab", "identity", "storage", "scripting", "tabs"], "host_permissions": ["https://app.getgptmail.com/", "*://mail.google.com/*", "*://outlook.live.com/*", "*://outlook.office.com/*", "*://outlook.office365.com/*"], "action": {"default_popup": "popup.html"}, "content_scripts": [{"matches": ["*://mail.google.com/*", "*://outlook.live.com/*", "*://outlook.office.com/*", "*://outlook.office365.com/*"], "js": ["src/content.js"], "css": ["styles/main.css"]}], "web_accessible_resources": [{"resources": ["src/content.js.map"], "matches": ["*://mail.google.com/*", "*://outlook.live.com/*", "*://outlook.office.com/*", "*://outlook.office365.com/*"]}], "background": {"service_worker": "background.js"}, "icons": {"16": "icons/icon16.png", "32": "icons/icon32.png", "48": "icons/icon48.png", "128": "icons/icon128.png"}}