{"update_url": "https://clients2.google.com/service/update2/crx", "name": "DevelopersIO_Search", "version": "1.0", "manifest_version": 2, "description": "DevelopersIO\u306e\u30b5\u30a4\u30c8\u5185\u691c\u7d22\u3092\u884c\u3046\u305f\u3081\u306e\u691c\u7d22\u30dc\u30c3\u30af\u30b9\u3067\u3059\u3002Google\u30b5\u30a4\u30c8\u5185\u691c\u7d22\u7d50\u679c\u3092\u5225\u30bf\u30d6\u3067\u8868\u793a\u3057\u307e\u3059\u3002", "icons": {"32": "icon_32.png", "48": "icon_48.png", "128": "icon_128.png"}, "browser_action": {"default_icon": {"16": "developersio.png"}, "default_popup": "popup.html"}}