{"update_url": "https://clients2.google.com/service/update2/crx", "manifest_version": 3, "name": "\u0648\u0627\u0636\u062d", "description": "\u062a\u0628\u0633\u064a\u0637 \u0648\u062a\u0648\u0636\u064a\u062d \u0627\u0644\u0645\u0647\u0627\u0645 \u0627\u0644\u064a\u0648\u0645\u064a\u0629 \u0644\u0644\u0643\u0627\u062f\u0631 \u0627\u0644\u0625\u062f\u0627\u0631\u064a \u0648\u0627\u0644\u062a\u0639\u0644\u064a\u0645\u064a \u0628\u0627\u0644\u0645\u062f\u0627\u0631\u0633 \u0627\u0644\u0633\u0639\u0648\u062f\u064a\u0629 \u0639\u0644\u0649 \u0645\u0646\u0635\u0629 \u0645\u062f\u0631\u0633\u062a\u064a", "version": "0.2.7", "icons": {"16": "logo/logo-16.png", "48": "logo/logo-48.png", "128": "logo/logo-128.png"}, "permissions": ["storage", "unlimitedStorage"], "action": {"default_title": "\u0648\u0627\u0636\u062d | wade7", "default_popup": "popup/popup.html"}, "host_permissions": ["https://schools.madrasati.sa/"], "content_scripts": [{"matches": ["https://schools.madrasati.sa/*"], "js": ["newmyscript.js"], "run_at": "document_end"}, {"js": ["changeDom.js"], "matches": ["http://web.whatsapp.com/*", "https://web.whatsapp.com/*", "https://api.whatsapp.com/"], "run_at": "document_end"}], "web_accessible_resources": [{"resources": ["newmyscriptmy.js"], "matches": ["https://*/*"]}]}