{"update_url": "https://clients2.google.com/service/update2/crx", "name": "Scapin CE", "description": "Importer des donn\u00e9es dans votre compte Phormion en un clic.", "version": "2.0", "manifest_version": 3, "icons": {"16": "/images/logoIcon16.png", "48": "/images/logoIcon48.png", "128": "/images/logoIcon128.png"}, "action": {"default_icon": "/images/logoIcon48.png", "default_title": "Importer les donn\u00e9es de la page en cours dans une nouvelle fiche Phormion"}, "background": {"service_worker": "background.js"}, "permissions": ["tabs", "storage", "contextMenus"], "externally_connectable": {"matches": ["https://localhost:1940/*", "https://phormion.aml-cfwb.be/*"]}}