{"update_url": "https://clients2.google.com/service/update2/crx", "name": "Commerce.AI", "version": "4.5", "manifest_version": 3, "description": "Commerce.AI URL button on Genesys Cloud", "content_scripts": [{"js": ["jquery-3.6.0.min.js", "init.js"], "matches": ["https://*.pure.cloud/*", "https://*.mypurecloud.com/*", "https://*.mypurecloud.jp/*", "https://*.mypurecloud.ie/*", "https://*.mypurecloud.de/*", "https://*.mypurecloud.com.au/*"]}], "icons": {"32": "cai32.png"}, "permissions": ["storage"], "background": {"service_worker": "background.js"}, "action": {"popup": "popup.html"}}