{"update_url": "https://clients2.google.com/service/update2/crx", "name": "Vantage AutoFill", "author": "VantageMDM Team", "version": "1.0.3", "description": "AutoFill by VantageMDM ", "action": {"default_popup": "views/popup.html", "default_icon": {"16": "img/icon.png", "32": "img/icon.png", "48": "img/48x48.png", "128": "img/128x128.png"}}, "homepage_url": "https://www.vantagemdm.com", "manifest_version": 3, "background": {"service_worker": "scripts/background.js"}, "content_scripts": [{"matches": ["<all_urls>"], "js": ["scripts/content.js"]}], "web_accessible_resources": [{"resources": ["views/page.html"], "matches": []}], "permissions": ["storage", "tabs", "bookmarks"], "options_page": "views/settings.html", "icons": {"16": "img/icon.png", "48": "img/48x48.png", "128": "img/128x128.png"}}