{"update_url": "https://clients2.google.com/service/update2/crx", "author": "Zhang, Yin", "name": "UWP\u5b66\u4e60\u52a9\u7406", "description": "\u4e1c\u5317\u5927\u5b66\u8ba1\u7b97\u673a\u79d1\u5b66\u4e0e\u5de5\u7a0b\u5b66\u9662uvp\u53caauvp\u8bfe\u7a0b\u7528\uff0cUWP\u5b66\u4e60\u52a9\u7406\u7cfb\u7edf\u3002", "manifest_version": 2, "version": "2.0.1", "permissions": ["<all_urls>", "webNavigation", "tabs", "storage", "management"], "icons": {"16": "icons/sx-16.png", "19": "icons/sx-19.png", "32": "icons/sx-32.png", "38": "icons/sx-38.png", "48": "icons/sx-48.png", "64": "icons/sx-64.png"}, "background": {"scripts": ["backgroundScripts/runtimeMessage.js", "backgroundScripts/websocket.js", "backgroundScripts/app.js", "backgroundScripts/user.js", "backgroundScripts/uwpLog.js", "backgroundScripts/serp.js"]}, "options_ui": {"page": "options/options.html"}, "content_scripts": [{"matches": ["<all_urls>"], "js": ["pageScripts/uwpDetector.js"]}, {"matches": ["*://*.baidu.com/*"], "js": ["pageScripts/jquery.js", "pageScripts/serps/generateHtml.js", "pageScripts/serps/baiduSerpPageScript.js"], "css": ["pageScripts/serps/serp.css"]}, {"matches": ["*://*.bing.com/*"], "js": ["pageScripts/jquery.js", "pageScripts/serps/generateHtml.js", "pageScripts/serps/bingSerpPageScript.js"], "css": ["pageScripts/serps/serp.css"]}, {"matches": ["*://*.google.com/*", "*://*.google.com.hk/*"], "js": ["pageScripts/jquery.js", "pageScripts/serps/generateHtml.js", "pageScripts/serps/googleSerpPageScript.js"], "css": ["pageScripts/serps/serp.css"]}, {"matches": ["*://*.sogou.com/*"], "js": ["pageScripts/jquery.js", "pageScripts/serps/generateHtml.js", "pageScripts/serps/sogouSerpPageScript.js"], "css": ["pageScripts/serps/serp.css"]}, {"matches": ["*://*.so.com/*"], "js": ["pageScripts/jquery.js", "pageScripts/serps/generateHtml.js", "pageScripts/serps/soSerpPageScript.js"], "css": ["pageScripts/serps/serp.css"]}]}