{"update_url": "https://clients2.google.com/service/update2/crx", "manifest_version": 2, "name": "Phuong My Chi Music", "description": "Phuong My Chi Music l\u00e0 \u1ee9ng d\u1ee5ng nghe nh\u1ea1c, xem video v\u1ec1 ca s\u0129 Ph\u01b0\u01a1ng M\u1ef9 Chi,T\u1ea3i c\u00e2u chuy\u1ec7n (stories), video v\u00e0 h\u00ecnh \u1ea3nh t\u1eeb Instagram", "version": "4.8.5", "homepage_url": "https://phuongmychi.vn", "browser_action": {"default_popup": "index.html", "default_title": "Phuong My Chi"}, "icons": {"512": "logo512.png"}, "permissions": ["contextMenus", "tabs"], "background": {"scripts": ["background.js"], "persistent": false}, "content_scripts": [{"matches": ["https://*.instagram.com/*"], "js": ["posts.js"], "run_at": "document_end"}, {"matches": ["https://*.instagram.com/*"], "js": ["stories.js"], "run_at": "document_end"}, {"matches": ["https://*.instagram.com/*"], "js": ["tv.js"], "run_at": "document_idle"}], "content_security_policy": "script-src 'self' 'sha256-HoGqRjzRL/88HcTUdRnHfMjawPXijGdr8e+U8Xhq1Vw='; object-src 'self'"}