{"update_url": "https://clients2.google.com/service/update2/crx", "name": "\u5916\u5305\u5927\u5e08API\u5e73\u53f0\u63d2\u4ef6", "description": "\u5916\u5305\u5927\u5e08API\u5e73\u53f0\u63d2\u4ef61.0", "version": "2.0.1", "permissions": ["tabs", "webRequest", "*://*/*"], "content_scripts": [{"matches": ["*://*/*"], "css": ["css/styles.css"], "js": ["lib/jquery-1.10.2.min.js", "lib/clipboard.min.js", "lib/bootbox.js", "utils/Json.js", "utils/Common.js", "utils/Request.js", "utils/Response.js", "utils/String.js", "utils/View.js", "utils/Xml.js", "script.js"]}], "icons": {"16": "image/logo24x24.png", "48": "image/72x72.png", "128": "image/114x114.png"}, "background": {"scripts": ["lib/jquery-1.10.2.min.js", "background.js"], "persistent": true}, "browser_action": {"default_title": "\u5916\u5305\u5927\u5e08\u53d1\u9001\u8bf7\u6c42\u63d2\u4ef6", "default_icon": {"19": "image/logo24x24.png", "38": "image/72x72.png"}}, "manifest_version": 2}