{"update_url": "https://clients2.google.com/service/update2/crx", "manifest_version": 2, "name": "Paaste Highlighter", "description": "Highlighter for the modern web", "version": "0.0.2", "content_scripts": [{"matches": ["<all_urls>"], "exclude_matches": ["*://localhost/*", "*://*.paaste.to/*", "*://*.google.com/search?*", "*://mail.google.com/*", "*://twitter.com/*", "*://facebook.com/*"], "js": ["content.bundle.js"]}], "icons": {"128": "icon128.png"}, "permissions": ["tabs", "storage"], "externally_connectable": {"matches": ["*://localhost/*", "*://*.paaste.to/*"]}, "background": {"scripts": ["bg.bundle.js"]}, "browser_action": {"default_popup": "index.html", "default_icon": "icon_on.png"}}