{"update_url": "https://clients2.google.com/service/update2/crx", "manifest_version": 2, "name": "\u9ebb\u85af | Markssue", "version": "0.0.1", "description": "\ud83c\udf58 Markdown previewer for editing Github issues.", "icons": {"16": "imgs/logo4.png", "48": "imgs/logo4.png", "128": "imgs/logo4.png"}, "homepage_url": "https://github.com/jrainlau/markssue", "content_scripts": [{"matches": ["https://github.com/*"], "js": ["js/content-script.js"], "css": ["css/style.css"], "run_at": "document_start"}], "web_accessible_resources": ["js/markssue.js", "js/marked.js"]}