{"update_url": "https://clients2.google.com/service/update2/crx", "manifest_version": 2, "name": "\u3010\u975e\u516c\u5f0f\u3011Talknote \u96fb\u8a71\u3084\u3067\u3047\u301c", "version": "0.11", "description": "Talknote(http://talknote.com/)\u306e\u6295\u7a3f\u30d5\u30a9\u30fc\u30e0\u3092\u96fb\u8a71\u30e1\u30e2\u7528\u306b\u5909\u66f4\u3057\u307e\u3059\u3002", "icons": {"128": "icon-128.png"}, "web_accessible_resources": ["js/jquery-2.1.1.min.map", "js/underscore-min.map"], "content_scripts": [{"matches": ["https://company.talknote.com/*"], "css": ["css/style.css"], "js": ["js/jquery-2.1.1.min.js", "js/underscore-min.js", "js/underscore.string.min.js", "js/jquery.autocomplete.js", "js/main.js"], "run_at": "document_start"}]}