{"update_url": "https://clients2.google.com/service/update2/crx", "name": "Alkohol Per Krona", "manifest_version": 2, "version": "1.1", "description": "Alkohol Per Krona hj\u00e4lper dig att lista ut om du f\u00e5r valuta f\u00f6r pengar hos Systembolaget! G\u00e5 in p\u00e5 alternativ f\u00f6r info", "permissions": ["https://www.systembolaget.se/dryck/*"], "options_page": "readme.html", "content_scripts": [{"matches": ["https://www.systembolaget.se/dryck/*"], "js": ["alkoholperkrona.js"]}], "icons": {"128": "images/icon128.png"}, "browser_action": {"default_icon": {"128": "images/icon128.png"}, "default_title": "Klicka F\u00f6r Info", "default_popup": "popup.html"}}