{"update_url": "https://clients2.google.com/service/update2/crx", "name": "ReferralCreate", "short_name": "ReferralCreate", "version": "1.0.1", "description": "Automatically pull data from EHRs and referral management platforms to effortlessly create new referrals in ReferralPlus.", "manifest_version": 3, "minimum_chrome_version": "88", "icons": {"16": "images/icon-16.png", "32": "images/icon-32.png", "48": "images/icon-48.png", "128": "images/icon-128.png"}, "action": {"default_icon": "images/icon-48.png", "default_title": "ReferralCreate", "default_popup": "html/router.html"}, "background": {"service_worker": "js/background.js"}, "permissions": ["activeTab", "storage", "contextMenus", "scripting"], "web_accessible_resources": [{"resources": ["html/*.html", "css/*.css", "js/*.js", "vendors/**/*.js"], "matches": ["<all_urls>"]}]}