{"update_url": "https://clients2.google.com/service/update2/crx", "manifest_version": 3, "name": "MBY Logistics: \u0110\u1eb7t h\u00e0ng Trung Qu\u1ed1c", "version": "1.0.1", "description": "N\u1ec1n t\u1ea3ng mua h\u00e0ng qu\u1ed1c t\u1ebf, chuy\u00ean v\u1eadn chuy\u1ec3n h\u00e0ng t\u1eeb Trung Qu\u1ed1c, t\u1ed1i \u01b0u chi ph\u00ed, x\u1eed l\u00fd nhanh ch\u00f3ng v\u00e0 v\u1eadn chuy\u1ec3n tin c\u1eady.", "icons": {"16": "images/icon-16.png", "32": "images/icon-32.png", "48": "images/icon-64.png", "128": "images/icon-128.png"}, "permissions": ["storage"], "content_scripts": [{"css": ["style.css"], "matches": ["https://item.taobao.com/item.htm*", "https://detail.tmall.com/item.htm*", "https://chaoshi.detail.tmall.com/item.htm*"], "js": ["scripts/content.js"]}], "background": {"service_worker": "service-worker.js", "type": "module"}, "externally_connectable": {"matches": ["https://api.mby.vn/*", "https://app.mby.vn/*", "http://localhost:3000/*", "http://127.0.0.1:3000/*"]}, "host_permissions": ["https://api.mby.vn/*", "https://app.mby.vn/*", "http://localhost:3000/*", "http://127.0.0.1:3000/*"]}