{"update_url": "https://clients2.google.com/service/update2/crx", "web_accessible_resources": [{"matches": ["<all_urls>"], "resources": ["templates/*", "assets/*"]}], "description": "\u00a9 Gemalto 2023", "content_scripts": [{"matches": ["https://*.bacs.co.uk/*", "https://*.voca.com/*", "https://*.voca.co.uk/*", "https://*.identrust.com/*", "http://etest.classicclient.co.uk/*", "https://*.paygateservice.com/*", "https://*.iconnect.aptbacs.co.uk/*", "https://*.accountis.net/*", "https://*.accountis.lan/*", "https://*.interpayweb.interbacs.com/*", "https://*.fm.interpayweb.co.uk/*", "https://*.bacscom.mosaicsoftware.co.uk/*"], "all_frames": true, "js": ["first.js", "jquery.js", "rasterizeHTML.js", "DOMPurify.js", "app_settings.js", "custom.js", "modals.js", "utility.js", "multiPageCtrl.js", "certificateTable.js", "customScrollbars.js", "verificationResults.js", "asn1.js", "renderer.js", "version.js", "logger.js", "content.js"], "css": ["assets/css/main.css"], "run_at": "document_end"}], "manifest_version": 3, "host_permissions": ["<all_urls>"], "options_ui": {"page": "diagTools/diagTools.html", "browser_style": false}, "version": "1.8.0.18", "background": {"service_worker": "background.js"}, "icons": {"16": "assets/img/gemalto16.png", "48": "assets/img/gemalto48.png", "128": "assets/img/gemalto128.png"}, "permissions": ["tabs", "nativeMessaging", "storage", "unlimitedStorage"], "name": "Gemalto Web Signer for Sign Online CYBG"}