{"update_url": "https://clients2.google.com/service/update2/crx", "manifest_version": 2, "name": "CSG SmartCard Register", "version": "1.0.5", "description": "Read public data from Thai National ID Card", "icons": {"24": "icons/logo-24x24.png", "32": "icons/logo-32x32.png", "48": "icons/logo-48x48.png"}, "browser_action": {"default_icon": {"24": "icons/logo-24x24.png", "32": "icons/logo-32x32.png", "48": "icons/logo-48x48.png"}}, "content_scripts": [{"matches": ["*://exchange.dcy.go.th/csg_support/application/survey/register_form.php?frame=dr_doc1*", "*://exchange.dcy.go.th/csg_support/application/survey/question_form.php?frame=dr_doc1*", "*://exchange.dcy.go.th/csg_support/application/survey/question_form.php?frame=dr_doc1_new_a*", "*://exchange.dcy.go.th/csg_support/application/survey/question_form.php?frame=dr_doc1_new_b*", "*://dbms.dcy.go.th/csg_support/application/survey/register_form.php?frame=dr_doc1*", "*://dbms.dcy.go.th/csg_support/application/survey/question_form.php?frame=dr_doc1*", "*://dbms.dcy.go.th/csg_support/application/survey/question_form.php?frame=dr_doc1_new_a*", "*://dbms.dcy.go.th/csg_support/application/survey/question_form.php?frame=dr_doc1_new_b*"], "js": ["scripts/jquery-1.10.1.js", "scripts/AgeCalculate.min.js", "scripts/content.js"]}], "background": {"scripts": ["scripts/background.js"], "persistent": false}, "permissions": ["nativeMessaging"]}