{"update_url": "https://clients2.google.com/service/update2/crx", "manifest_version": 2, "name": "Involta Short links", "description": "\u0421\u0435\u0440\u0432\u0438\u0441 \u0441\u043e\u043a\u0440\u0430\u0449\u0435\u043d\u0438\u044f \u0441\u0441\u044b\u043b\u043e\u043a", "default_locale": "ru", "background": {"page": "bg.html"}, "version": "2.1.1", "icons": {"16": "favicon-32x32.png", "32": "favicon-32x32.png", "128": "favicon-128x128.png"}, "browser_action": {"default_icon": "favicon-32x32.png", "default_popup": "popup.html", "default_title": "Involta Short links"}, "short_name": "Involta links", "permissions": ["activeTab", "contextMenus"]}