{"update_url": "https://clients2.google.com/service/update2/crx", "name": "DarkMode for Zalo", "description": "Let's enjoy zalo with dark colors", "icons": {"16": "/imgs/icon16.png", "48": "/imgs/icon48.png", "128": "/imgs/icon128.png"}, "version": "0.0.1", "author": "Quang S\u00e1ng", "manifest_version": 3, "action": {"default_title": "DarkMode for Zalo", "default_icon": "/imgs/icon128.png"}, "permissions": ["tabs", "storage", "scripting"], "host_permissions": ["https://chat.zalo.me/*"], "background": {"service_worker": "js/background.js"}}