{"update_url": "https://clients2.google.com/service/update2/crx", "manifest_version": 2, "name": "\u6587\u6848\u732b-\u8ba9\u7075\u611f\u5192\u51fa\u6765", "version": "0.0.2", "description": "\u8ba9\u7075\u611f\u5192\u51fa\u6765", "icons": {"16": "img/icon.png", "48": "img/icon.png", "128": "img/icon.png"}, "homepage_url": "https://wam.hqzt.vip", "browser_action": {"default_icon": "img/icon.png", "default_title": "\u6587\u6848\u732b-\u8ba9\u7075\u611f\u5192\u51fa\u6765", "default_popup": "popup.html"}}