{"update_url": "https://clients2.google.com/service/update2/crx", "name": "bilibili\u6f2b\u753b \u7ffb\u8a33\u8868\u793a\u30c4\u30fc\u30eb", "version": "1.1.0", "manifest_version": 2, "description": "bilibili\u6f2b\u753b\u306b\u7ffb\u8a33\u30c6\u30ad\u30b9\u30c8\u3092\u8868\u793a\u30fb\u7de8\u96c6\u3067\u304d\u308b\u3088\u3046\u306b\u306a\u308b\u62e1\u5f35\u6a5f\u80fd\u3067\u3059", "content_scripts": [{"matches": ["https://manga.bilibili.com/mc*"], "js": ["js/chunk-vendors.js", "js/app.js"]}], "homepage_url": "https://github.com/reimer0204/bilibili-manga-translate-supporter", "icons": {"16": "icon/16.png", "48": "icon/48.png", "128": "icon/128.png"}, "permissions": ["https://manga.bilibili.com/mc*", "storage"]}