{"update_url": "https://clients2.google.com/service/update2/crx", "manifest_version": 2, "name": "Maestro Label Designer Font Finder", "author": "Online Labels, LLC", "description": "Use the fonts installed on your computer in Maestro Label Designer by OnlineLabels.com.", "version": "1.0.1", "icons": {"16": "icon16.png", "48": "icon48.png", "128": "icon128.png"}, "browser_action": {"default_icon": "icon48.png"}, "background": {"scripts": ["background.js"], "persistent": false}, "content_scripts": [{"matches": ["*://*.onlinelabels.com/*"], "js": ["contentScript.js"]}], "permissions": ["fontSettings"]}