{"update_url": "https://clients2.google.com/service/update2/crx", "name": "YonkaSoft Page Speed", "version": "1.1", "homepage_url": "https://yonkasoft.com/", "description": "YonkaSoft Page Speed gezindi\u011finiz t\u00fcm web sitelerinin y\u00fcklenme h\u0131z\u0131n\u0131 \u00f6l\u00e7er ve sonradan kontrol edebilmeniz i\u00e7in kaydeder.", "manifest_version": 3, "content_scripts": [{"js": ["./foreground.js"], "matches": ["<all_urls>"], "run_at": "document_start"}], "action": {"default_popup": "./popup.html"}, "permissions": ["storage"], "icons": {"128": "./img/logo.png"}}