{"update_url": "https://clients2.google.com/service/update2/crx", "name": "Hide Junk", "short_name": "Hides All Junk Crypto Junk", "version": "2.1", "manifest_version": 2, "description": "Hides All Junk From Twitter", "background": {"page": "background.html"}, "browser_action": {"name": "Manipulate DOM", "icons": ["icon.png"], "default_icon": "icon.png", "default_popup": "popup.html"}, "icons": {"16": "icon16.png", "48": "icon48.png", "128": "icon128.png"}, "permissions": ["http://twitter.com/*", "storage", "https://twitter.com/*"], "content_scripts": [{"js": ["background.js"], "matches": ["http://twitter.com/*", "https://twitter.com/*"]}]}