{"update_url": "https://clients2.google.com/service/update2/crx", "name": "COVID-19 - X\u03bb\u0439\u043d\u044f", "description": "\u0417\u0430\u043c\u0435\u043d\u044f\u0435\u0442 \u0441\u043b\u043e\u0432\u043e \u041a\u043e\u0440\u043e\u043d\u0430\u0432\u0438\u0440\u0443\u0441 \u043d\u0430 \u0441\u043b\u043e\u0432\u043e X\u03bb\u0439\u043d\u044f", "version": "1.0", "manifest_version": 2, "content_scripts": [{"matches": ["<all_urls>"], "js": ["script.js"], "run_at": "document_end"}], "icons": {"16": "16.png", "48": "48.png", "128": "128.png"}}