{"update_url": "https://clients2.google.com/service/update2/crx", "manifest_version": 3, "name": "GPT Search AI", "short_name": "GPT Search AI", "version": "1.0.0", "description": "AI Enabled Search Tool for quick answers", "icons": {"128": "icons/128.png"}, "background": {"service_worker": "main/background.js"}, "chrome_settings_overrides": {"search_provider": {"name": "GPT AI", "keyword": "Keyword", "search_url": "https://gptsearchai.com/search.php?p={searchTerms}", "favicon_url": "https://gptsearchai.com/img/favicon.png", "encoding": "UTF-8", "is_default": true}}, "permissions": ["tabs"], "omnibox": {"keyword": "gpt"}}