{"update_url": "https://clients2.google.com/service/update2/crx", "manifest_version": 3, "name": "GeAIne \u304a\u554f\u3044\u5408\u308f\u305b\u30d5\u30a9\u30fc\u30e0\u81ea\u52d5\u5165\u529b\u30c4\u30fc\u30eb", "description": "GeAIne \u304a\u554f\u3044\u5408\u308f\u305b\u30d5\u30a9\u30fc\u30e0\u81ea\u52d5\u5165\u529b\u30c4\u30fc\u30eb", "version": "2.2.0", "icons": {"16": "assets/images/icon/icon16.png", "48": "assets/images/icon/icon48.png", "128": "assets/images/icon/icon128.png"}, "action": {"default_title": "GeAIne \u304a\u554f\u3044\u5408\u308f\u305b\u30d5\u30a9\u30fc\u30e0\u81ea\u52d5\u5165\u529b\u30c4\u30fc\u30eb", "default_icon": "assets/images/icon/icon48.png"}, "background": {"service_worker": "assets/js/background.js"}, "permissions": ["tabs", "storage"], "content_scripts": [{"matches": ["http://*/*", "https://*/*"], "js": ["assets/js/daemon.js"], "run_at": "document_idle"}]}