{"update_url": "https://clients2.google.com/service/update2/crx", "name": "Triobo - digital publishing", "description": "Triobo is an all-in-one software for creating and publishing interactive publications for Apple, Android, Amazon and for the web.", "default_locale": "en", "short_name": "Triobo", "manifest_version": 2, "version": "1.3.0.4", "app": {"urls": ["http://www.triobo.com/", "http://editor.triobo.com/"], "launch": {"web_url": "http://editor.triobo.com"}}, "icons": {"128": "triobo_icon_128.png"}, "permissions": ["unlimitedStorage", "notifications"]}