{"update_url": "https://clients2.google.com/service/update2/crx", "name": "Happy Harvesting", "description": "Connect similar vegetables but you have limited time. try to make big chains and get power-ups to extend time and extra score. ", "version": "1.0.0.4", "manifest_version": 2, "icons": {"128": "icon_128.png"}, "app": {"urls": ["http://netfreedomgames.com/chrome_apps/happy_harvesting/index.html"], "launch": {"web_url": "http://netfreedomgames.com/chrome_apps/happy_harvesting/index.html"}}}