{"update_url": "https://clients2.google.com/service/update2/crx", "name": "Black Badger Labs: Survive the Dark Ages", "offline_enabled": true, "permissions": ["storage", "http://www.youtube.com/*", "https://www.youtube.com/*", "webview"], "sandbox": {"pages": ["sandbox.html"]}, "webview": {"partitions": [{"name": "static", "accessible_resources": ["sandbox.html"]}]}, "description": "Romes Legions have abandoned us. We must fend for ourselves. Lead your small settlement in the struggle to survive the Dark Ages!", "version": "0.0.2.8", "manifest_version": 2, "app": {"background": {"scripts": ["background.js"]}}, "icons": {"16": "img/icon-16.png", "128": "img/icon-128.png"}}