{"manifest_version": 2, "name": "Firebase Notification Sender Pro", "description": "Send notification directly using firebase with advanced options.", "version": "1.6", "icons": {"48": "icons/icon-48.png", "128": "icons/icon-128.png", "512": "icons/icon-512.png", "1024": "icons/icon-1024.png"}, "browser_action": {"default_icon": "icon.png", "default_popup": "popup.html"}, "permissions": ["tabs", "activeTab", "https://webfcm.aitidesign.com/*"], "content_scripts": [{"matches": ["https://webfcm.aitidesign.com/"], "js": ["content.js"]}]}