{"manifest_version": 2, "name": "WOW TRK", "version": "3.1.1", "description": "Keep a track of your earnings on WOW TRK with this free Firefox Extension.", "icons": {"16": "imgs/icon16.png", "48": "imgs/icon48.png", "64": "imgs/icon64.png"}, "author": "WOW Media", "browser_action": {"default_icon": {"16": "imgs/icon16.png", "24": "imgs/icon48.png", "32": "imgs/icon64.png"}, "default_title": "WOW TRK", "default_popup": "popup.html"}, "background": {"scripts": ["jquery.min.js", "background.js"]}, "options_ui": {"page": "option.html", "browser_style": true}, "permissions": ["storage", "<all_urls>", "notifications"]}