{"manifest_version": 2, "name": "__MSG_extName__", "version": "0.2.0", "description": "__MSG_extDescription__", "icons": {"48": "icons/icon48.png", "128": "icons/icon128.png"}, "applications": {"gecko": {"id": "pricealarm@icopron.ch", "strict_min_version": "45.0"}}, "short_name": "__MSG_shortName__", "default_locale": "en", "content_scripts": [{"matches": ["*://amazon.de/*", "*://amazon.fr/*", "*://amazon.it/*", "*://amazon.es/*", "*://amazon.co.uk/*", "*://amazon.com/*", "*://amazon.com.mx/*", "*://amazon.ca/*", "*://amazon.co.jp/*", "*://*.amazon.de/*", "*://*.amazon.fr/*", "*://*.amazon.it/*", "*://*.amazon.es/*", "*://*.amazon.co.uk/*", "*://*.amazon.com/*", "*://*.amazon.com.mx/*", "*://*.amazon.ca/*", "*://*.amazon.co.jp/*"], "js": ["jquery-3.1.1.min.js", "myFrame.js"]}]}