{"manifest_version": 2, "name": "twitter\u30af\u30ea\u30c3\u30af\u753b\u50cf\u30c0\u30a6\u30f3\u30ed\u30fc\u30c0", "description": "twitter\u306e\u30c4\u30a4\u30fc\u30c8\u753b\u50cf\u3092\u30c0\u30a6\u30f3\u30ed\u30fc\u30c9\u3059\u308b\u30bd\u30d5\u30c8\u3067\u3059\u3002", "version": "1.0.2", "icons": {"18": "icon.png"}, "permissions": ["*://pbs.twimg.com/*", "downloads", "tabs", "storage"], "browser_action": {"default_icon": "icon.png"}, "options_ui": {"page": "options.html"}, "background": {"scripts": ["background.js"]}, "content_scripts": [{"matches": ["*://twitter.com/*"], "all_frames": true, "js": ["contentscripts.js"]}], "browser_specific_settings": {"gecko": {"id": "{4cb40330-7809-4984-a448-651f2a3a8148}"}}}