{"manifest_version": 2, "name": "CFCA CryptoKit.YZZG Extension", "version": "3.4.0.1", "description": "CFCA Security Application Development Kit", "author": "CFCA", "background": {"scripts": ["background.js"]}, "applications": {"gecko": {"id": "cryptokit_yunzhuzhigang@cfca.com.cn", "strict_min_version": "50.0"}}, "content_scripts": [{"matches": ["http://*.yzzg.tech/*", "https://*.yzzg.tech/*"], "js": ["content.js"], "run_at": "document_end"}], "permissions": ["http://*.yzzg.tech/*", "https://*.yzzg.tech/*", "nativeMessaging", "activeTab"], "icons": {"16": "icon-16.png", "48": "icon-48.png", "128": "icon-128.png"}}