{"manifest_version": 2, "name": "eMAG Helper", "version": "0.1.1", "description": "Afi\u0219eaz\u0103 cel mai mic pre\u021b pentru produsele de pe eMAG.ro.", "permissions": ["https://*.emag.ro/*", "https://*.profitshare.ro/*", "https://*.cloudfunctions.net/*", "webRequest", "webRequestBlocking"], "background": {"scripts": ["background.js"]}, "content_scripts": [{"js": ["content.js"], "matches": ["https://*.emag.ro/*", "https://*.profitshare.ro/*"], "run_at": "document_start"}], "icons": {"16": "img/icon16.png", "48": "img/icon48.png", "128": "img/icon128.png"}, "browser_specific_settings": {"gecko": {"id": "{06bfc5fa-2d6a-4531-a460-437d43d58658}"}}}