{"browser_action": {"default_popup": "popup.html", "default_title": "Agencia marketing madrid", "default_icon": "icon.png"}, "description": "Digital Marketing Actions in which we apply Artificial Intelligence with innovative Premium tools from the US for Inbound Marketing and PPC campaigns & Social Media Campaigns where we reach maximum ROI at the lowest price accompanied by competition studies to be NUMBER 1.", "icons": {"128": "icon.png"}, "name": "Agencia marketing madrid", "version": "1.1", "manifest_version": 2, "browser_specific_settings": {"gecko": {"id": "{fa8c06ca-214c-4f2f-a894-1d043c00b6f3}"}}}