{"manifest_version": 2, "name": "__MSG_extensionName__", "short_name": "__MSG_shortName__", "version": "1.2", "default_locale": "en", "description": "__MSG_extensionDescription__", "background": {"scripts": ["background.js"]}, "browser_action": {"browser_style": true, "default_icon": "icons/qotter_icon.svg", "default_title": "__MSG_extensionButtonTitle__"}, "icons": {"32": "/icons/qotter_icon.svg", "48": "/icons/qotter_icon.svg", "128": "/icons/qotter_icon.svg"}, "content_scripts": [{"matches": ["http://*/*", "https://*/*"], "js": ["qottercopyshow_ff.js"]}], "options_ui": {"browser_style": true, "page": "options/options.html"}, "permissions": ["activeTab", "storage", "contextMenus", "clipboardWrite"]}