{"manifest_version": 2, "name": "\u4e00\u952e\u51c0\u5316\u53cd\u9ed1", "short_name": "\u51c0\u5316\u53cd\u9ed1", "version": "2.0.10", "description": "Auto clean and complain for Roy.", "icons": {"16": "son_16.png", "48": "son_48.png", "128": "son_128.png"}, "browser_action": {"default_icon": "son_16.png", "default_title": "\u4e00\u952e\u51c0\u5316\u53cd\u9ed1"}, "permissions": ["http://*/", "bookmarks", "tabs", "history"], "content_scripts": [{"matches": ["https://m.weibo.cn/*", "https://service.account.weibo.com/report*", "https://www.baidu.com/s*"], "js": ["Auto_clean_report.js"], "run_at": "document_end"}]}